Metadata-Version: 1.1
Name: segmentation-phenix
Version: 0.1.6
Summary: Mixture model segmentation for Phenix images
Home-page: https://github.com/mmasinas/segmentation_phenix
Author: Matej Usaj
Author-email: m.usaj@utoronto.ca
License: UNKNOWN
Download-URL: https://github.com/mmasinas/segmentation_phenix/archive/master.zip
Keywords: mixture,model,segmentation
Platform: UNKNOWN
